securesteg/__init__.py
securesteg/securesteg.py
securesteg-0.1.0.dist-info/LICENSE
securesteg-0.1.0.dist-info/METADATA
securesteg-0.1.0.dist-info/WHEEL
securesteg-0.1.0.dist-info/top_level.txt
securesteg-0.1.0.dist-info/RECORD
